DX/__init__.py
DX/channel.py
DX/contract.py
DX/crypto.py
DX/result.py
DX/utils.py
DX/wallet.py
DX.py-0.3.1.dist-info/LICENSE
DX.py-0.3.1.dist-info/METADATA
DX.py-0.3.1.dist-info/WHEEL
DX.py-0.3.1.dist-info/top_level.txt
DX.py-0.3.1.dist-info/RECORD
