Metadata-Version: 2.1
Name: DX.py
Version: 0.3.1
Summary: Python SDK for the DX Network, the world's first real-time marketplace for structured data
Home-page: https://dx.network
Author: The DX Network
Author-email: info@dx.network
License: MIT
Platform: UNKNOWN
Classifier: Programming Language :: Python :: 3
Classifier: License :: OSI Approved :: MIT License
Classifier: Operating System :: OS Independent
Requires-Dist: web3
Requires-Dist: eth-keyfile
Requires-Dist: eth-keys
Requires-Dist: eth-abi
Requires-Dist: requests
Requires-Dist: pygments
Requires-Dist: asn1
Requires-Dist: python-dateutil
